batao.py
padho.py
setup.py
dikhao/__init__.py
dikhao/config.py
dikhao/search.py
dikhao/sync.py
dikhao/util.py
dikhao.egg-info/PKG-INFO
dikhao.egg-info/SOURCES.txt
dikhao.egg-info/dependency_links.txt
dikhao.egg-info/entry_points.txt
dikhao.egg-info/requires.txt
dikhao.egg-info/top_level.txt
dikhao/aws/__init__.py
dikhao/aws/ec2.py
dikhao/aws/route53.py
dikhao/database/__init__.py
dikhao/database/redis_handler.py