Metadata-Version: 1.1
Name: dikhao
Version: 0.0.11
Summary: Dikhao: A quick view of all related EC2 & Route53 resources
Home-page: https://github.com/rohit01/dikhao
Author: Rohit Gupta
Author-email: hello@rohit.io
License: UNKNOWN
Keywords: dikhao,ec2,aws,route53,platform,iaas
Platform: UNKNOWN
Classifier: Programming Language :: Python
Classifier: Operating System :: OS Independent
Classifier: License :: OSI Approved :: MIT License
Classifier: Intended Audience :: Developers
Classifier: Development Status :: 4 - Beta
Classifier: Environment :: Console
Classifier: Topic :: Utilities
Classifier: License :: OSI Approved :: MIT License
